mits_similarity_BJP/__init__.py
mits_similarity_BJP/hamming_distance.py
mits_similarity_BJP/jaccard_coefficient.py
mits_similarity_BJP/overlap_coefficient.py
mits_similarity_BJP-0.1.dist-info/LICENSE
mits_similarity_BJP-0.1.dist-info/METADATA
mits_similarity_BJP-0.1.dist-info/WHEEL
mits_similarity_BJP-0.1.dist-info/top_level.txt
mits_similarity_BJP-0.1.dist-info/RECORD
